adafruit_circuitpython_max7219-1.5.19.dist-info/licenses/LICENSE
adafruit_max7219/__init__.py
adafruit_max7219/bcddigits.py
adafruit_max7219/matrices.py
adafruit_max7219/max7219.py
adafruit_circuitpython_max7219-1.5.19.dist-info/METADATA
adafruit_circuitpython_max7219-1.5.19.dist-info/WHEEL
adafruit_circuitpython_max7219-1.5.19.dist-info/top_level.txt
adafruit_circuitpython_max7219-1.5.19.dist-info/RECORD
